trecrun/__init__.py
trecrun-0.3.0.dist-info/LICENSE
trecrun-0.3.0.dist-info/METADATA
trecrun-0.3.0.dist-info/WHEEL
trecrun-0.3.0.dist-info/top_level.txt
trecrun-0.3.0.dist-info/RECORD
