Metadata-Version: 2.1
Name: trecrun
Version: 0.3.0
Summary: Library for working with TREC run files
Home-page: https://github.com/capreolus-ir/trecrun
Author: Andrew Yates
Author-email: one-name-then-the-next@gmail.com
Classifier: Programming Language :: Python :: 3
Classifier: Operating System :: OS Independent
Requires-Python: >=3.8
License-File: LICENSE
Requires-Dist: ir-measures
Requires-Dist: numpy
Requires-Dist: scikit-learn
Requires-Dist: smart-open
